Frasty/Fraction.py
Frasty/__init__.py
frasty-1.1.0.dist-info/licenses/LICENSE
frasty-1.1.0.dist-info/METADATA
frasty-1.1.0.dist-info/WHEEL
frasty-1.1.0.dist-info/top_level.txt
frasty-1.1.0.dist-info/RECORD
