Metadata-Version: 2.4
Name: frasty
Version: 1.1.0
Summary: Frasty is a python library that allows you to easily calculate fractions
Home-page: https://github.com/Tina-1300/Frasty
Author: Tina
Author-email: tina.xytrfgthuji1348@gmail.com
License: MIT
Classifier: Programming Language :: Python :: 3
Classifier: License :: OSI Approved :: MIT License
Classifier: Operating System :: OS Independent
Classifier: Intended Audience :: Developers
Classifier: Topic :: Scientific/Engineering :: Mathematics
Requires-Python: >=3.13.0
License-File: LICENSE
Dynamic: license-file
